arcstack_api/__init__.py
arcstack_api/api.py
arcstack_api/conf.py
arcstack_api/decorators.py
arcstack_api/endpoint.py
arcstack_api/errors.py
arcstack_api/logger.py
arcstack_api/meta.py
arcstack_api/middleware.py
arcstack_api/mixins.py
arcstack_api/responses.py
arcstack_api/serializers.py
arcstack_api/signature.py
arcstack_api/utils.py
arcstack_django_api-0.2.1.dist-info/METADATA
arcstack_django_api-0.2.1.dist-info/WHEEL
arcstack_django_api-0.2.1.dist-info/RECORD
